spytial/__init__.py
spytial/annotations.py
spytial/dataclass_builder.py
spytial/evaluator.py
spytial/evaluator_template.html
spytial/input_template.html
spytial/provider_system.py
spytial/requirements.txt
spytial/utils.py
spytial/visualizer.py
spytial/visualizer_template.html
spytial/domain_relationalizers/__init__.py
spytial/domain_relationalizers/base.py
spytial/domain_relationalizers/dataclass_relationalizer.py
spytial/domain_relationalizers/dict_relationalizer.py
spytial/domain_relationalizers/fallback_relationalizer.py
spytial/domain_relationalizers/generic_object_relationalizer.py
spytial/domain_relationalizers/list_relationalizer.py
spytial/domain_relationalizers/primitive_relationalizer.py
spytial/domain_relationalizers/set_relationalizer.py
spytial/domain_relationalizers/tuple_relationalizer.py
spytial_diagramming-0.6.4.dist-info/licenses/LICENSE
spytial_diagramming-0.6.4.dist-info/METADATA
spytial_diagramming-0.6.4.dist-info/WHEEL
spytial_diagramming-0.6.4.dist-info/top_level.txt
spytial_diagramming-0.6.4.dist-info/RECORD
