Metadata-Version: 2.4
Name: spytial_diagramming
Version: 0.6.4
Summary: sPyTial: Spatial Python visualization with declarative constraints
Home-page: https://github.com/sidprasad/spytial
Author: Siddhartha Prasad
Author-email: 
License: MIT
Project-URL: Homepage, https://github.com/sidprasad/spytial
Project-URL: Repository, https://github.com/sidprasad/spytial
Project-URL: Issues, https://github.com/sidprasad/spytial/issues
Keywords: visualization,diagrams,spatial,constraints,data-structures
Classifier: Development Status :: 3 - Alpha
Classifier: Intended Audience :: Developers
Classifier: Intended Audience :: Education
Classifier: Intended Audience :: Science/Research
Classifier: Programming Language :: Python :: 3
Classifier: Programming Language :: Python :: 3.8
Classifier: Programming Language :: Python :: 3.9
Classifier: Programming Language :: Python :: 3.10
Classifier: Programming Language :: Python :: 3.11
Classifier: Programming Language :: Python :: 3.12
Classifier: Topic :: Scientific/Engineering :: Visualization
Classifier: Topic :: Software Development :: Libraries :: Python Modules
Requires-Python: >=3.8
License-File: LICENSE
Requires-Dist: jinja2>=3.0.0
Requires-Dist: pyyaml>=6.0
Requires-Dist: ipython>=8.0.0
Provides-Extra: dev
Requires-Dist: pytest>=7.0.0; extra == "dev"
Requires-Dist: flake8>=6.0.0; extra == "dev"
Requires-Dist: black>=23.0.0; extra == "dev"
Provides-Extra: docs
Requires-Dist: mkdocs>=1.5.0; extra == "docs"
Requires-Dist: mkdocs-material>=9.0.0; extra == "docs"
Requires-Dist: mkdocstrings[python]>=0.24.0; extra == "docs"
Dynamic: home-page
Dynamic: license-file
Dynamic: requires-python
